hezar/__init__.py
hezar/builders.py
hezar/configs.py
hezar/constants.py
hezar/data/__init__.py
hezar/data/data_collators.py
hezar/data/data_samplers.py
hezar/data/dataset_processors.py
hezar/data/datasets/__init__.py
hezar/data/datasets/dataset.py
hezar/data/datasets/image_captioning_dataset.py
hezar/data/datasets/ocr_dataset.py
hezar/data/datasets/sequence_labeling_dataset.py
hezar/data/datasets/speech_recognition_dataset.py
hezar/data/datasets/text_classification_dataset.py
hezar/data/datasets/text_summarization_dataset.py
hezar/embeddings/__init__.py
hezar/embeddings/embedding.py
hezar/embeddings/fasttext.py
hezar/embeddings/word2vec.py
hezar/metrics/__init__.py
hezar/metrics/accuracy.py
hezar/metrics/bleu.py
hezar/metrics/cer.py
hezar/metrics/f1.py
hezar/metrics/metric.py
hezar/metrics/precision.py
hezar/metrics/recall.py
hezar/metrics/rouge.py
hezar/metrics/seqeval.py
hezar/metrics/wer.py
hezar/models/__init__.py
hezar/models/backbone/__init__.py
hezar/models/backbone/bert/__init__.py
hezar/models/backbone/bert/bert.py
hezar/models/backbone/bert/bert_config.py
hezar/models/backbone/distilbert/__init__.py
hezar/models/backbone/distilbert/distilbert.py
hezar/models/backbone/distilbert/distilbert_config.py
hezar/models/backbone/roberta/__init__.py
hezar/models/backbone/roberta/roberta.py
hezar/models/backbone/roberta/roberta_config.py
hezar/models/backbone/vit/__init__.py
hezar/models/backbone/vit/vit.py
hezar/models/backbone/vit/vit_config.py
hezar/models/image2text/__init__.py
hezar/models/image2text/beit_roberta/__init__.py
hezar/models/image2text/beit_roberta/beit_roberta_image2text.py
hezar/models/image2text/beit_roberta/beit_roberta_image2text_config.py
hezar/models/image2text/crnn/__init__.py
hezar/models/image2text/crnn/crnn_decode_utils.py
hezar/models/image2text/crnn/crnn_image2text.py
hezar/models/image2text/crnn/crnn_image2text_config.py
hezar/models/image2text/trocr/__init__.py
hezar/models/image2text/trocr/trocr_image2text.py
hezar-0.42.0.dist-info/LICENSE
hezar-0.42.0.dist-info/METADATA
hezar-0.42.0.dist-info/WHEEL
hezar-0.42.0.dist-info/RECORD
