Metadata-Version: 2.1
Name: hezar
Version: 0.42.0
Summary: Hezar: The all-in-one AI library for Persian, supporting a wide variety of tasks and modalities!
Home-page: https://github.com/hezarai
License: Apache-2.0
Keywords: packaging,poetry
Author: Aryan Shekarlaban
Author-email: arxyzan@gmail.com
Maintainer: Aryan Shekarlaban
Maintainer-email: arxyzan@gmail.com
Requires-Python: >=3.10.0
Classifier: Development Status :: 5 - Production/Stable
Classifier: Intended Audience :: Developers
Classifier: License :: OSI Approved :: Apache Software License
Classifier: Programming Language :: Python
Classifier: Programming Language :: Python :: 3
Classifier: Programming Language :: Python :: 3.10
Classifier: Programming Language :: Python :: 3.11
Classifier: Programming Language :: Python :: 3.12
Classifier: Programming Language :: Python :: 3.13
Classifier: Topic :: Scientific/Engineering :: Artificial Intelligence
Classifier: Topic :: Software Development :: Libraries :: Python Modules
Provides-Extra: all
Provides-Extra: audio
Provides-Extra: dev
Provides-Extra: embeddings
Provides-Extra: metrics
Provides-Extra: nlp
Provides-Extra: trainer
Provides-Extra: vision
Requires-Dist: accelerate (>=0.27.0) ; extra == "trainer" or extra == "all"
Requires-Dist: datasets (>=2.9.0) ; extra == "all"
Requires-Dist: gensim (==4.3.2) ; extra == "embeddings" or extra == "all"
Requires-Dist: huggingface_hub (>=0.12.0)
Requires-Dist: jiwer (>=3) ; extra == "nlp" or extra == "audio" or extra == "metrics" or extra == "all"
Requires-Dist: librosa (>=0.10.0) ; extra == "audio" or extra == "all"
Requires-Dist: nltk (>=3.8.0) ; extra == "nlp" or extra == "metrics" or extra == "all"
Requires-Dist: numpy (==1.24.*) ; extra == "embeddings" or extra == "all"
Requires-Dist: omegaconf (>=2.3.0)
Requires-Dist: opencv-python ; extra == "vision" or extra == "all"
Requires-Dist: pandas ; extra == "trainer" or extra == "all"
Requires-Dist: pillow (>=9,<=10) ; extra == "vision" or extra == "all"
Requires-Dist: rouge_score ; extra == "nlp" or extra == "metrics" or extra == "all"
Requires-Dist: scikit-learn (>=1.0.0) ; extra == "metrics" or extra == "all"
Requires-Dist: scipy (==1.11.4) ; extra == "embeddings" or extra == "all"
Requires-Dist: seqeval (>=1.2.0) ; extra == "nlp" or extra == "metrics" or extra == "all"
Requires-Dist: soundfile (>=0.12.0) ; extra == "audio" or extra == "all"
Requires-Dist: tensorboard (>=2.10.0) ; extra == "trainer" or extra == "all"
Requires-Dist: tokenizers (>=0.13.0)
Requires-Dist: torch (>=1.10.0)
Requires-Dist: torchvision ; extra == "vision" or extra == "all"
Requires-Dist: transformers (>=4.28.0)
Project-URL: Documentation, https://hezarai.github.io/hezar/
Project-URL: Repository, https://github.com/hezarai/hezar
